plsm/__init__.py
plsm/config_manager.py
plsm/service_manager.py
plsm/status_manager.py
plsm-1.0.1.dist-info/METADATA
plsm-1.0.1.dist-info/WHEEL
plsm-1.0.1.dist-info/licenses/LICENSE
plsm-1.0.1.dist-info/RECORD
