Metadata-Version: 2.4
Name: plsm
Version: 1.0.1
Summary: Python Linux Service Manager - 专注于Linux系统服务管理的Python库
Project-URL: Homepage, https://gitee.com/liumou_site/plsm
Project-URL: Repository, https://gitee.com/liumou_site/plsm
Project-URL: Documentation, https://gitee.com/liumou_site/plsm
Author-email: 坐公交也用券 <liumou.site@qq.com>
License: MIT
License-File: LICENSE
Keywords: init,linux,management,service,systemd
Classifier: Development Status :: 3 - Alpha
Classifier: Intended Audience :: Developers
Classifier: Intended Audience :: System Administrators
Classifier: License :: OSI Approved :: MIT License
Classifier: Operating System :: POSIX :: Linux
Classifier: Programming Language :: Python :: 3
Classifier: Programming Language :: Python :: 3.7
Classifier: Programming Language :: Python :: 3.8
Classifier: Programming Language :: Python :: 3.9
Classifier: Programming Language :: Python :: 3.10
Classifier: Programming Language :: Python :: 3.11
Classifier: Programming Language :: Python :: 3.12
Classifier: Topic :: System :: Systems Administration
Classifier: Topic :: Utilities
Requires-Python: >=3.7
Requires-Dist: dataclasses; python_version < '3.8'
